[
  {
    "id":1,
    "des":"In this 5 day class we will explore artist Monet , Van Gogh , among others and then recreate paintings usings crayon and water color . Students will fun learning about the artists and creating their own art inspired by their work",
    "image":[
       {
        "img1":"https://i.ibb.co/c2YYjH9/vintage-landscape-with-gondolas-1160-162.png",
        "img2":"https://i.ibb.co/jMX2Znw/oil-painting-beautiful-lotus-flower-1232-1978.png",
        "img3":"https://i.ibb.co/GpzyD5F/graffiti-children-bicycle-1122-2206.png"
       }
    ]
  }
]